{
  "aor": 0.0011736882129277566,
  "aqi": 0.006326016527249683,
  "bids_meta": {
    "CoilElements": "HC1-6",
    "EchoTime": 0.03,
    "EffectiveEchoSpacing": 0.000579993,
    "FlipAngle": 35,
    "MultibandAccelerationFactor": 6,
    "MultisliceMode": "interleaved",
    "PhaseEncodingDirection": "j-",
    "RepetitionTime": 0.4,
    "SliceThickness": 4,
    "SliceTiming": [
      0.044,
      0.27217,
      0.12019,
      0.34816,
      0.19618,
      0.0442,
      0.27217,
      0.12019,
      0.34816,
      0.19618,
      0.0442,
      0.27217,
      0.12019,
      0.34816,
      0.19618,
      0.0442,
      0.27217,
      0.12019,
      0.34816,
      0.19618,
      0.0442,
      0.27217,
      0.12019,
      0.34816,
      0.19618,
      0.0442,
      0.27217,
      0.12019,
      0.34816,
      0.19618
    ],
    "Slices": 30,
    "TR": 0.4,
    "TaskName": "read task",
    "TotalReadoutTime": 0.0463994,
    "TotalReadoutTimeFSL": 0.0458194,
    "dataset": "ds003988",
    "modality": "bold",
    "run_id": 4,
    "subject_id": "28",
    "task_id": "read"
  },
  "dummy_trs": 6,
  "dvars_nstd": 20.686097842296935,
  "dvars_std": 1.1469636731725894,
  "dvars_vstd": 1.0114158288578694,
  "efc": 0.42178202206999976,
  "fber": 14615.6982421875,
  "fd_mean": 0.07150632925887283,
  "fd_num": 12,
  "fd_perc": 1.520912547528517,
  "fwhm_avg": 1.8004130555555555,
  "fwhm_x": 1.80257,
  "fwhm_y": 1.9774566666666666,
  "fwhm_z": 1.6212125,
  "gcor": 0.0156069,
  "gsr_x": -0.019823430106043816,
  "gsr_y": 0.01734464056789875,
  "provenance": {
    "md5sum": "b6c9a5ed1d485222f416b62799bc5986",
    "settings": {
      "fd_thres": 0.2,
      "testing": false
    },
    "software": "mriqc",
    "version": "23.0.0",
    "webapi_port": null,
    "webapi_url": "https://mriqc.nimh.nih.gov/api/v1"
  },
  "size_t": 789,
  "size_x": 80,
  "size_y": 80,
  "size_z": 30,
  "snr": 7.243438539029933,
  "spacing_tr": 0.4000000059604645,
  "spacing_x": 3.0,
  "spacing_y": 3.0,
  "spacing_z": 4.0,
  "summary_bg_k": 67.26002763885856,
  "summary_bg_mad": 46.31769479848294,
  "summary_bg_mean": 189.37095642089844,
  "summary_bg_median": 56.51203918457031,
  "summary_bg_n": 131536.0,
  "summary_bg_p05": 20.054182052612305,
  "summary_bg_p95": 813.7094421386719,
  "summary_bg_stdv": 457.515625,
  "summary_fg_k": 2.305339146342922,
  "summary_fg_mad": 851.2844220695403,
  "summary_fg_mean": 6928.88037109375,
  "summary_fg_median": 6884.0380859375,
  "summary_fg_n": 24809.0,
  "summary_fg_p05": 5551.2642578125,
  "summary_fg_p95": 8469.973437499999,
  "summary_fg_stdv": 950.3634643554688,
  "tsnr": 69.5374904552009
}